biorat/__init__.py
biorat/ontology.py
bioRAT-0.2.0.dist-info/LICENSE.txt
bioRAT-0.2.0.dist-info/METADATA
bioRAT-0.2.0.dist-info/WHEEL
bioRAT-0.2.0.dist-info/top_level.txt
bioRAT-0.2.0.dist-info/RECORD
